packaging_demo/__init__.py
packaging_demo/cities.json
packaging_demo/colorized_demo.py
packaging_demo/my_file.py
packaging_demo/my_other_file.py
packaging_demo/slow.py
packaging_demo/states_info.py
packaging_demo/my_folder/__init__.py
packaging_demo/my_folder/another-cities.json
packaging_demo/my_folder/my_nested_file.py
packaging_demo/my_folder/my_sub_package/__init__.py
packaging_demo/my_folder/my_sub_package/nested_module.py
packaging_demo_avr-0.0.11.dist-info/METADATA
packaging_demo_avr-0.0.11.dist-info/WHEEL
packaging_demo_avr-0.0.11.dist-info/top_level.txt
packaging_demo_avr-0.0.11.dist-info/RECORD
