Metadata-Version: 2.1
Name: packaging-demo-avr
Version: 0.0.11
Summary: Demo for Python Packaging
Author-email: Amit Vikram Raj <avr13405@gmail.com>
License: MIT
Project-URL: Repository, https://github.com/avr2002/python-packaging
Project-URL: Documentation, https://github.com/avr2002/python-packaging/blob/main/README.md
Keywords: python,bash,makefile,pypi,ci-cd,setuptools,wheels,package-development,github-actions,pypi-package,pre-commit-hooks,pyproject-toml,gitactions-workflow,github-actions-enabled,pre-commit-ci,pre-commit-config
Classifier: Programming Language :: Python :: 3
Requires-Python: >=3.8
Requires-Dist: numpy
Requires-Dist: fastapi
Requires-Dist: importlib-metadata ; python_version < "3.10"
Provides-Extra: all
Requires-Dist: packaging-demo-avr[colors,dev] ; extra == 'all'
Provides-Extra: colors
Requires-Dist: rich ; extra == 'colors'
Provides-Extra: dev
Requires-Dist: ruff ; extra == 'dev'
Requires-Dist: mypy ; extra == 'dev'
Requires-Dist: black ; extra == 'dev'
Requires-Dist: packaging-demo-avr[release,static-code-qa,test] ; extra == 'dev'
Provides-Extra: release
Requires-Dist: build ; extra == 'release'
Requires-Dist: twine ; extra == 'release'
Provides-Extra: static-code-qa
Requires-Dist: pre-commit ; extra == 'static-code-qa'
Provides-Extra: test
Requires-Dist: pytest ; extra == 'test'
Requires-Dist: pytest-cov ; extra == 'test'
